{
  "id": "006",
  "type": "implementation",
  "status": "pending",
  "description": "Create Models directory: src/RealmsOfIdle.Client.Blazor/Models/",
  "acceptanceCriteria": [],
  "owns": [],
  "touches": [
    "src/RealmsOfIdle.Client.Blazor"
  ],
  "blockedBy": [],
  "claimedBy": null,
  "history": [
    {
      "status": "claimed",
      "agent": "implementer-2",
      "timestamp": "2026-02-09T16:39:38.808Z"
    },
    {
      "status": "pending",
      "agent": "implementer-2",
      "timestamp": "2026-02-09T16:43:10.987Z",
      "note": "reclaimed on startup"
    },
    {
      "status": "claimed",
      "agent": "implementer-1",
      "timestamp": "2026-02-09T16:43:12.256Z"
    },
    {
      "status": "failed",
      "agent": "implementer-1",
      "timestamp": "2026-02-09T16:43:14.871Z"
    },
    {
      "status": "pending",
      "agent": "manual-reset",
      "timestamp": "2026-02-09T16:59:13.916Z",
      "note": "manually reset from failed"
    }
  ],
  "retries": 0
}
